{
  "schema_version": "0.1",
  "last_updated": "2026-04-05",
  "components": [
    {
      "file": "specs/button.spec.json",
      "component": "Button",
      "aliases": ["Btn", "CTA", "action button", "regular button"],
      "category": "actions",
      "description": "Interactive element that triggers an action. Contains a text label and optional leading/trailing icon slots. Has contained (filled), outlined (border), and ghost (text-only) type variants.",
      "anatomy_keywords": ["Container", "Label", "Icon L", "Icon R", "Spinner", "contained", "outlined", "ghost", "button", "interactive", "label", "icon slot"],
      "related": ["IconButton", "TextButton"]
    }
  ]
}
